README
setup.py
applepushnotification/__init__.py
applepushnotification/service.py
applepushnotification.egg-info/PKG-INFO
applepushnotification.egg-info/SOURCES.txt
applepushnotification.egg-info/dependency_links.txt
applepushnotification.egg-info/top_level.txt