Metadata-Version: 1.0
Name: applepushnotification
Version: 0.1.1
Summary: Apple Push Notification Service connector
Home-page: https://github.com/martinkou/applepushnotification
Author: Kou Man Tong
Author-email: martinkou@tixxme.com
License: BSD
Keywords: APNS push notification Apple
Platform: Any
